zohoSolCon/__init__.py
zohoSolCon/auth.py
zohoSolCon/books/__init__.py
zohoSolCon/books/contact_persons.py
zohoSolCon/books/contacts.py
zohoSolCon/books/estimates.py
zohoSolCon/books/invoices.py
zohoSolCon/books/salesorders.py
zohoSolCon/books/tests.py
zohoSolCon/creator/__init__.py
zohoSolCon/creator/data.py
zohoSolCon/crm/__init__.py
zohoSolCon/crm/attachments.py
zohoSolCon/crm/bulk_api.py
zohoSolCon/crm/modules.py
zohoSolCon/crm/notes.py
zohoSolCon/crm/org.py
zohoSolCon/crm/profiles.py
zohoSolCon/crm/records.py
zohoSolCon/crm/related_list.py
zohoSolCon/crm/roles.py
zohoSolCon/crm/subforms.py
zohoSolCon/crm/tags.py
zohoSolCon/crm/territory.py
zohoSolCon/crm/test.py
zohoSolCon/crm/users.py
zohoSolCon/desk/__init__.py
zohoSolCon/desk/accounts.py
zohoSolCon/desk/agents.py
zohoSolCon/desk/contacts.py
zohoSolCon/desk/departments.py
zohoSolCon/desk/profiles.py
zohoSolCon/desk/roles.py
zohoSolCon/desk/teams.py
zohoSolCon/desk/tickets.py
zohoSolCon/inventory/__init__.py
zohoSolCon/inventory/composite_items.py
zohoSolCon/inventory/contacts.py
zohoSolCon/inventory/items.py
zohoSolCon/inventory/organizations.py
zohoSolCon-0.4.7.post6.dist-info/METADATA
zohoSolCon-0.4.7.post6.dist-info/WHEEL
zohoSolCon-0.4.7.post6.dist-info/top_level.txt
zohoSolCon-0.4.7.post6.dist-info/RECORD
