Metadata-Version: 2.1
Name: zohoSolCon
Version: 0.4.7-6
Summary: Implementation tools for Zoho CRM
Home-page: UNKNOWN
Author: Dylan Garrett
Author-email: dylan.g@zohocorp.com
License: UNKNOWN
Keywords: zoho,crm,api
Platform: UNKNOWN
